flutter_smartstart
