Metadata-Version: 2.1
Name: flutter-smartstart
Version: 0.5
Summary: A CLI tool to create and customize Flutter projects with a clean code folder structure
Home-page: https://github.com/iam-bkpl/flutter-smartstart
Author: Kapil Bhandari
Author-email: iam.bkpl031@gmail.com
Classifier: Programming Language :: Python :: 3
Classifier: License :: OSI Approved :: MIT License
Classifier: Operating System :: OS Independent
Requires-Python: >=3.6
Requires-Dist: prompt_toolkit
